README.md
setup.cfg
setup.py
dist_Gaussian/Binomialdistribution.py
dist_Gaussian/Gaussiandistribution.py
dist_Gaussian/Generaldistribution.py
dist_Gaussian/__init__.py
dist_Gaussian.egg-info/PKG-INFO
dist_Gaussian.egg-info/SOURCES.txt
dist_Gaussian.egg-info/dependency_links.txt
dist_Gaussian.egg-info/not-zip-safe
dist_Gaussian.egg-info/top_level.txt