Metadata-Version: 1.0
Name: dist-Gaussian
Version: 0.1
Summary: Gaussian distributions
Home-page: UNKNOWN
Author: Szilvia Jakab
Author-email: UNKNOWN
License: UNKNOWN
Platform: UNKNOWN
